pyimgkit/__init__.py
pyimgkit/measure/__init__.py
pyimgkit/measure/_bbox.py
pyimgkit-0.0.11.dist-info/DESCRIPTION.rst
pyimgkit-0.0.11.dist-info/METADATA
pyimgkit-0.0.11.dist-info/RECORD
pyimgkit-0.0.11.dist-info/WHEEL
pyimgkit-0.0.11.dist-info/metadata.json
pyimgkit-0.0.11.dist-info/top_level.txt
