Metadata-Version: 2.0
Name: pyimgkit
Version: 0.0.11
Summary: UNKNOWN
Home-page: UNKNOWN
Author: Jihye Yun
Author-email: UNKNOWN
License: UNKNOWN
Platform: UNKNOWN
Requires-Dist: numpy (>=1.18.1)
Requires-Dist: scipy (>=1.4.1)
